icmodel/__init__.py
icmodel/fastkNN.py
icmodel/figplot.py
icmodel/ic.py
icmodel/model/Cell_Develop_Time_Prediction.model
icmodel/model/Cell_Type_Classification.model
icmodel/model/Cell_Type_Classification.npy
icmodel-0.0.3.dist-info/METADATA
icmodel-0.0.3.dist-info/WHEEL
icmodel-0.0.3.dist-info/top_level.txt
icmodel-0.0.3.dist-info/RECORD
